__init__.py
src/modeling/trainer.py
src/utils/__init__.py
src/utils/config.py
src/utils/data_processing.py
src/visuals/__init__.py
src/visuals/base_analysis.py
src/visuals/temporal_analysis.py
autokeystroke_rb3-0.0.2.dist-info/METADATA
autokeystroke_rb3-0.0.2.dist-info/WHEEL
autokeystroke_rb3-0.0.2.dist-info/licenses/LICENCE
autokeystroke_rb3-0.0.2.dist-info/RECORD
