Metadata-Version: 2.1
Name: autokeystroke_rb3
Version: 0.0.2
Summary: A python package for automatically processing and modeling keystroke log data
Project-URL: Homepage, https://github.com/Ryan6407/AutoKeystroke
Project-URL: Issues, https://github.com/Ryan6407/AutoKeystroke/issues
Author-email: Ryan Barretto <ryanbarretto70@gmail.com>
License-File: LICENCE
Classifier: License :: OSI Approved :: MIT License
Classifier: Operating System :: OS Independent
Classifier: Programming Language :: Python :: 3
Requires-Python: >=3.8
